README.md
setup.py
apmondatalib/AIslandClient.py
apmondatalib/Constants.py
apmondatalib/DBConnection.py
apmondatalib/DataFetcher.py
apmondatalib/Sensor.py
apmondatalib/__init__.py
apmondatalib.egg-info/PKG-INFO
apmondatalib.egg-info/SOURCES.txt
apmondatalib.egg-info/dependency_links.txt
apmondatalib.egg-info/requires.txt
apmondatalib.egg-info/top_level.txt