Metadata-Version: 1.1
Name: apmondatalib
Version: 0.0.8.2
Summary: Datalib for AIsland project
Home-page: https://bitbucket.org/pful/pydatalib
Author: Daeyeon Joo
Author-email: daeyeonjoo@p-ful.com
License: MIT License
Platform: UNKNOWN
Classifier: Development Status :: 4 - Beta
Classifier: Intended Audience :: Developers
Classifier: License :: OSI Approved :: MIT License
Classifier: Programming Language :: Python :: 3
